outlook_autoreply_helper/__init__.py
outlook_autoreply_helper/__main__.py
outlook_autoreply_helper/auth.py
outlook_autoreply_helper/command.py
outlook_autoreply_helper/settings.py
outlook_autoreply_helper/util.py
outlook_autoreply_helper-0.1.2.dist-info/METADATA
outlook_autoreply_helper-0.1.2.dist-info/WHEEL
outlook_autoreply_helper-0.1.2.dist-info/entry_points.txt
outlook_autoreply_helper-0.1.2.dist-info/licenses/LICENSE
outlook_autoreply_helper-0.1.2.dist-info/RECORD
