Metadata-Version: 2.3
Name: outlook-autoreply-helper
Version: 0.1.2
Summary: A Python helper library to automatically manage Outlook auto-reply settings via the Microsoft Graph API.
Author-email: Jens Keiner <jens.keiner@gmail.com>
License: Apache-2.0
Requires-Python: >=3.10
Requires-Dist: azure-identity>=1.19.0
Requires-Dist: azure-keyvault-secrets>=4.9.0
Requires-Dist: jinja2>=3.0.0
Requires-Dist: msal-extensions>=1.2.0
Requires-Dist: msal>=1.29.0
Requires-Dist: pydantic-settings>=2.3.0
Requires-Dist: pydantic>=2.3.0
Requires-Dist: requests>=2.27.0
